cooperate/__init__.py
cooperate/__main__.py
cooperate/concurrency.py
cooperate/executionner.py
cooperate/modes.py
cooperate/nodes.py
cooperate/renderers.py
cooperate-0.3.1.dist-info/DESCRIPTION.rst
cooperate-0.3.1.dist-info/entry_points.txt
cooperate-0.3.1.dist-info/METADATA
cooperate-0.3.1.dist-info/metadata.json
cooperate-0.3.1.dist-info/pbr.json
cooperate-0.3.1.dist-info/RECORD
cooperate-0.3.1.dist-info/top_level.txt
cooperate-0.3.1.dist-info/WHEEL
