Metadata-Version: 2.0
Name: cooperate
Version: 0.3.1
Summary: Distribute commands to many nodes
Home-page: https://github.com/johnnoone/cooperate
Author: Xavier Barbosa
Author-email: clint.northwood@gmail.com
License: UNKNOWN
Keywords: infrastructure,asyncio
Platform: UNKNOWN
Classifier: Development Status :: 3 - Alpha
Classifier: Intended Audience :: Developers
Classifier: License :: OSI Approved :: BSD License
Classifier: Operating System :: OS Independent
Classifier: Programming Language :: Python :: 3.3
Classifier: Programming Language :: Python :: 3.4
Classifier: Topic :: System :: Clustering
Requires-Dist: aioutils
Requires-Dist: PyYAML
Requires-Dist: asyncio; python_version=="3.3"
